floisy/__init__.py
floisy/cli.py
floisy/container.py
floisy-0.1.1.dist-info/METADATA
floisy-0.1.1.dist-info/WHEEL
floisy-0.1.1.dist-info/entry_points.txt
floisy-0.1.1.dist-info/RECORD
