Metadata-Version: 2.1
Name: floisy
Version: 0.1.1
Summary: 
License: MIT
Author: Slava Vishnyakov
Author-email: bomboze@gmail.com
Requires-Python: >=3.12,<4.0
Classifier: License :: OSI Approved :: MIT License
Classifier: Programming Language :: Python :: 3
Classifier: Programming Language :: Python :: 3.12
Requires-Dist: uvicorn (>=0.30.6,<0.31.0)
